examples/basic_usage.py
openjobs/__init__.py
openjobs/http_utils.py
openjobs/logger.py
openjobs/processor.py
openjobs/py.typed
openjobs/scraper.py
openjobs/utils.py
openjobs/config/tech_stacks.json
openjobs-0.1.0.dist-info/licenses/LICENSE
tests/__init__.py
tests/conftest.py
tests/test_http_utils.py
tests/test_processor.py
tests/test_processor_mocked.py
tests/test_scraper.py
tests/test_scraper_mocked.py
tests/test_utils.py
openjobs-0.1.0.dist-info/METADATA
openjobs-0.1.0.dist-info/WHEEL
openjobs-0.1.0.dist-info/entry_points.txt
openjobs-0.1.0.dist-info/top_level.txt
openjobs-0.1.0.dist-info/RECORD
