Metadata-Version: 2.4
Name: openjobs
Version: 0.1.0
Summary: AI-powered job scraper - extract job listings from any careers page using Firecrawl + Gemini AI. Handles JavaScript-heavy sites, ATS systems, and React/Next.js SPAs.
Home-page: https://github.com/yourusername/openjobs
Author: OpenJobs Contributors
License-Expression: MIT
Project-URL: Homepage, https://github.com/federicodeponte/openjobs
Project-URL: Documentation, https://github.com/federicodeponte/openjobs#readme
Project-URL: Bug Tracker, https://github.com/federicodeponte/openjobs/issues
Project-URL: Source, https://github.com/federicodeponte/openjobs
Project-URL: Changelog, https://github.com/federicodeponte/openjobs/releases
Keywords: job-scraper,careers-page-scraper,web-scraping,firecrawl,gemini-ai,job-listings,job-board,recruitment,hiring,ats-scraper,applicant-tracking-system,careers-api,job-extraction,ai-scraper,javascript-scraper,spa-scraper,react-scraper,nextjs-scraper
Classifier: Development Status :: 4 - Beta
Classifier: Intended Audience :: Developers
Classifier: Intended Audience :: Information Technology
Classifier: Operating System :: OS Independent
Classifier: Programming Language :: Python :: 3
Classifier: Programming Language :: Python :: 3.9
Classifier: Programming Language :: Python :: 3.10
Classifier: Programming Language :: Python :: 3.11
Classifier: Programming Language :: Python :: 3.12
Classifier: Topic :: Internet :: WWW/HTTP :: Indexing/Search
Classifier: Topic :: Internet :: WWW/HTTP :: Dynamic Content
Classifier: Topic :: Software Development :: Libraries :: Python Modules
Classifier: Topic :: Text Processing :: Markup :: HTML
Classifier: Typing :: Typed
Requires-Python: >=3.9
License-File: LICENSE
Requires-Dist: requests>=2.28.0
Requires-Dist: tenacity>=8.0.0
Provides-Extra: dev
Requires-Dist: pytest>=7.0.0; extra == "dev"
Requires-Dist: pytest-cov>=4.0.0; extra == "dev"
Requires-Dist: black>=23.0.0; extra == "dev"
Requires-Dist: ruff>=0.1.0; extra == "dev"
Dynamic: home-page
Dynamic: license-file
Dynamic: requires-python
